World_of_Warships_replays_parser-3.3.0.data/scripts/replay_parser.py
replay_unpack/__init__.py
replay_unpack/replay_reader.py
World_of_Warships_replays_parser-3.3.0.dist-info/METADATA
World_of_Warships_replays_parser-3.3.0.dist-info/WHEEL
World_of_Warships_replays_parser-3.3.0.dist-info/top_level.txt
World_of_Warships_replays_parser-3.3.0.dist-info/RECORD
