Metadata-Version: 2.1
Name: World-of-Warships-replays-parser
Version: 3.3.0
Summary: Utility which loads .wowsreplay file, "plays" it in memory and produces results in json format
Home-page: UNKNOWN
Author: Oleksandr Shyshatskyi
Author-email: shalal545@gmail.com
License: MIT
Platform: UNKNOWN
